README.rst
setup.cfg
setup.py
pptx_template/__init__.py
pptx_template/chart.py
pptx_template/cli.py
pptx_template/core.py
pptx_template/pptx_util.py
pptx_template/pyel.py
pptx_template/text.py
pptx_template/xlsx_model.py
pptx_template_fork.egg-info/PKG-INFO
pptx_template_fork.egg-info/SOURCES.txt
pptx_template_fork.egg-info/dependency_links.txt
pptx_template_fork.egg-info/entry_points.txt
pptx_template_fork.egg-info/requires.txt
pptx_template_fork.egg-info/top_level.txt
test/test_cli.py
test/test_pyel.py
test/test_table.py
test/test_text.py
test/test_xlsx_model.py