Metadata-Version: 1.1
Name: pptx-template-fork
Version: 0.2.7.6
Summary: The PowerPoint presentation builder using template.pptx (without support in cli)
Home-page: https://github.com/skar404/pptx-template
Author: Reki Murakami
Author-email: skar404@gmail.com
License: Apache-2.0
Keywords: powerpoint,ppt,pptx
Platform: UNKNOWN
Classifier: Development Status :: 3 - Alpha
Classifier: Topic :: Utilities
Classifier: Programming Language :: Python :: 3
Classifier: Programming Language :: Python :: 3.5
Classifier: Programming Language :: Python :: 3.6
Classifier: License :: OSI Approved :: Apache Software License
Classifier: Operating System :: OS Independent
